setup.py
algorithmRunners/__init__.py
algorithmRunners/grainedGaRunner.py
algorithmRunners/launcher.py
algorithmRunners/masterSlaveGaRunner.py
examples/__init__.py
examples/coarseGrained.py
examples/fineGrained.py
examples/masterSlave.py
examples/runCoarseGrainedExample.py
examples/runFineGrainedExample.py
examples/runMasterSlaveExample.py
geneticAlgorithms/__init__.py
geneticAlgorithms/coarseGrainedBase.py
geneticAlgorithms/fineGrainedBase.py
geneticAlgorithms/geneticBase.py
geneticAlgorithms/geneticGrainedBase.py
geneticAlgorithms/masterSlaveBase.py
geneticAlgorithms/masterSlaveFitness.py
parallel_ga_processing.egg-info/PKG-INFO
parallel_ga_processing.egg-info/SOURCES.txt
parallel_ga_processing.egg-info/dependency_links.txt
parallel_ga_processing.egg-info/top_level.txt